src/bitorder.sv
`default_nettype none
`timescale 1ns / 1ps

//module here
module bitorder (
    input wire clk,
    input wire rst,
    input wire axiiv,
    input wire [1:0] axiid,

    output logic [1:0] axiod,
    output logic axiov
);
    //read1 -> flip1 and read2 -> flip2 and output1 -> output2  
    logic read_buff1; 
    logic readout_buff1;
    logic readout_buff2;
    logic read_buff2; 

    logic [15:0] b1_count; 
    logic [15:0] b2_count;

    logic [7:0] buff1;
    logic [7:0] buff2;

    always_comb begin
        if (rst) begin
            axiov = 0;
            axiod = 0;
        end else begin
            case ({read_buff1, readout_buff1, readout_buff2, read_buff2})
                4'b1000: begin
                    axiov = 0;
                end
                4'b0100: begin
                    if (b1_count > 0) begin
                        axiov = 1;
                        if (b1_count > 3) begin
                            axiod = buff1[7:6];
                        end else if (b1_count > 2) begin
                            axiod = buff1[5:4];
                        end else if (b1_count > 1) begin
                            axiod = buff1[3:2];
                        end else if (b1_count > 0) begin
                            axiod = buff1[1:0];
                        end
                    end else begin
                        axiov = 0;
                    end
                end
                4'b0010: begin
                    if (b2_count > 0) begin
                        axiov = 1;
                        if (b2_count > 3) begin
                            axiod = buff2[7:6];
                        end else if (b2_count > 2) begin
                            axiod = buff2[5:4];
                        end else if (b2_count > 1) begin
                            axiod = buff2[3:2];
                        end else if (b2_count > 0) begin
                            axiod = buff2[1:0];
                        end
                    end else begin
                        axiov = 0;
                    end
                end
                4'b0001: begin
                    axiov = 0;
                end
            endcase
        end
    end

    always_ff @(posedge clk) begin
        if (rst) begin
            buff1 <= 8'd0;
            buff2 <= 8'd0;
            b1_count <= 0;
            b2_count <= 0;
            read_buff1 <= 1;
            read_buff2 <= 0;
            readout_buff1 <= 0;
            readout_buff2 <= 0;
        end else begin
            case ({read_buff1, readout_buff1, readout_buff2, read_buff2})
                4'b1000: begin
                    if (axiiv) begin
                        b1_count <= b1_count + 1;
                        if (b1_count < 1) begin
                            buff1[1:0] <= axiid; 
                        end else if (b1_count < 2) begin
                            buff1[3:2] <= axiid; 
                        end else if (b1_count < 3) begin
                            buff1[5:4] <= axiid; 
                        end else if (b1_count < 4) begin
                            buff1[7:6] <= axiid; 
                            read_buff1 <= 0;
                            readout_buff1 <= 1;
                        end
                    end else begin
                        b1_count <=0;
                        buff1 <= 8'd0;
                        buff2 <= 8'd0;
                    end
                end
                4'b0100: begin
                    if (b1_count > 0) begin
                        b1_count <= b1_count - 1;
                    end
                    if (axiiv) begin
                        b2_count <= b2_count + 1;
                        if (b2_count < 1) begin
                            buff2[1:0] <= axiid; 
                        end else if (b2_count < 2) begin
                            buff2[3:2] <= axiid; 
                        end else if (b2_count < 3) begin
                            buff2[5:4] <= axiid; 
                        end else if (b2_count < 4) begin
                            buff2[7:6] <= axiid; 
                            readout_buff1 <= 0;
                            readout_buff2 <= 1;
                        end
                    end else if (b1_count == 0 & b2_count < 3) begin
                        b2_count <= 0;
                        buff2 <= 8'd0;
                        readout_buff1 <= 0;
                        read_buff2 <= 1;
                    end else begin
                        buff2 <= 0;
                        b2_count <= 0;
                    end
                end
                4'b0010: begin
                    if (b2_count > 0) begin
                        b2_count <= b2_count - 1;
                    end
                    if (axiiv) begin
                        b1_count <= b1_count + 1;
                        if (b1_count < 1) begin
                            buff1[1:0] <= axiid; 
                        end else if (b1_count < 2) begin
                            buff1[3:2] <= axiid; 
                        end else if (b1_count < 3) begin
                            buff1[5:4] <= axiid; 
                        end else if (b1_count < 4) begin
                            buff1[7:6] <= axiid; 
                            readout_buff1 <= 1;
                            readout_buff2 <= 0;
                        end
                    end else if (b2_count == 0 & b1_count < 3) begin
                        b1_count <= 0;
                        buff1 <= 8'd0;
                        readout_buff2 <= 0;
                        read_buff1 <= 1;
                    end else begin
                        buff1 <= 0;
                        b1_count <= 0;
                    end
                end
                4'b0001: begin
                    if (axiiv) begin
                        b2_count <= b2_count + 1;
                        if (b2_count < 1) begin
                            buff2[1:0] <= axiid; 
                        end else if (b2_count < 2) begin
                            buff2[3:2] <= axiid; 
                        end else if (b2_count < 3) begin
                            buff2[5:4] <= axiid; 
                        end else if (b2_count < 4) begin
                            buff2[7:6] <= axiid; 
                            read_buff2 <= 0;
                            readout_buff2 <= 1;
                        end
                    end else begin
                        b2_count <= 0;
                        buff2 <= 8'd0;
                        buff1 <= 8'd0;
                    end
                end
            endcase
        end
    end
endmodule

`default_nettype wire

src/transmit.sv
`default_nettype none
`timescale 1ns / 1ps

//module here
module transmit (
    input wire eth_clk,
    input wire eth_rst,

    input wire [10:0] hcount,
    input wire [9:0] vcount, 
    input wire [10:0] player_x,
    input wire [10:0] player_y,
    input wire [8:0] direction,
    input wire [2:0] game_stat, 

    output logic [1:0] eth_txd,
    output logic eth_txen
);

//TODO: checksum, bitorder swap? 

logic [511:0] message; 
logic [511:0] buffer;
logic counter;
logic [1:0] state; 

logic [1:0] bit_axiid;
logic bit_axiiv; 
logic [1:0] bit_axiod;
logic bit_axiov;

logic [55:0] preamble;
assign preamble = 56'h55_55_55_55_55_55_55;
logic [7:0] sfd;
assign sfd = 8'b11010101;
logic [47:0] dest_addr;
assign dest_addr = 48'hFF_FF_FF_FF_FF_FF; 
logic [47:0] source_addr;
assign source_addr = 48'hFF_FF_FF_FF_FF_FF; 
logic [15:0] len;
assign len = 16'h00_00;
logic [31:0] fcs;
assign fcs = 32'hCBF43926; //needs to be determined from checksum 
logic [39:0] data;
assign data = {{player_x, 1'b0}, {player_y, 1'b0}, {direction, 3'd0}, {game_stat, 1'b0}};

assign message = {preamble, sfd, dest_addr, source_addr, len, data, 264'b0, fcs}; //, source_addr, len, message, fcs}; //263'b0, 

// Might Need this
bitorder b1(.clk(eth_clk),
            .rst(eth_rst),
            .axiiv(bit_axiiv),
            .axiid(bit_axiid),
            .axiod(bit_axiod),
            .axiov(bit_axiov));

always_ff @(posedge eth_clk) begin
    if (eth_rst) begin
        counter <= 0;
        state <= 0;
        bit_axiiv <= 0;
        bit_axiid <= 0;
    end else begin
        case (state)
            2'b00: begin
                eth_txen <= 0;
                eth_txd <= 0;
                if (hcount[10:0] == 1024 && vcount[9:0] == 768) begin
                    $displayh(message);
                    buffer <= message;
                    state <= 1;
                end
            end
            2'b01: begin
                if (buffer != 0) begin
                    bit_axiiv <= 1;
                    bit_axiid <= buffer[511:510];
                    buffer <= {buffer[509:0], 2'b0};
                end else if (buffer == 0) begin
                    bit_axiiv <= 0;
                    bit_axiid <= 0;
                end

                if (bit_axiov == 1) begin
                    eth_txen <= 1;
                    eth_txd <= bit_axiod;
                end else if (bit_axiov == 0 && buffer == 0) begin
                    state <= 0;
                    eth_txen <= 0;
                    eth_txd <= 0;
                end
            end
        endcase
    end
end
    
endmodule

`default_nettype wire

sim/transmit_tb.sv
`timescale 1ns / 1ps
`default_nettype none

module transmit_tb;
    logic eth_clk;
    logic eth_rst;

    logic [10:0] hcount;
    logic [9:0] vcount;
    logic [10:0] player_x;
    logic [10:0] player_y;
    logic [8:0] dir;
    logic [2:0] game_stat; 

    logic [1:0] eth_txd;
    logic eth_txen;

    transmit t1(.eth_clk(eth_clk),
                .eth_rst(eth_rst),
                .hcount(hcount),
                .vcount(vcount),
                .player_x(player_x),
                .player_y(player_y),
                .direction(dir),
                .game_stat(game_stat),
                .eth_txd(eth_txd),
                .eth_txen(eth_txen));

    
    always begin
        #10;  //every 10 ns switch...so period of clock is 20 ns...50 MHz clock
        eth_clk = !eth_clk;
        // 1 clock cycle = 20
    end

    //initial block...this is our test simulation
    initial begin
        $dumpfile("transmit.vcd"); //file to store value change dump (vcd)
        $dumpvars(0,transmit_tb); //store everything at the current level and below
        $display("Starting Sim"); //print nice message
        eth_clk = 0; //initialize clk (super important)
        eth_rst = 1; //reset system
        #20; //hold high for a few clock cycles
        eth_rst=0;
        hcount=0;
        vcount=0;
        player_x = 8;
        player_y = 8;
        dir = 90;
        game_stat = 1;
        #20;

        hcount = 1024;
        vcount = 768;
        #20;

        hcount = 0;
        vcount = 0;

        // #40; 
        // hcount = 1024;
        // vcount = 768;

        #10000;
        $display("Finishing Sim"); //print nice message
        $finish;

    end
endmodule //counter_tb

`default_nettype wire

transmit.vcd
$date
	Fri Dec 02 23:44:50 2022
$end
$version
	Icarus Verilog
$end
$timescale
	1ps
$end
$scope module transmit_tb $end
$var wire 1 ! eth_txen $end
$var wire 2 " eth_txd [1:0] $end
$var reg 9 # dir [8:0] $end
$var reg 1 $ eth_clk $end
$var reg 1 % eth_rst $end
$var reg 3 & game_stat [2:0] $end
$var reg 11 ' hcount [10:0] $end
$var reg 11 ( player_x [10:0] $end
$var reg 11 ) player_y [10:0] $end
$var reg 10 * vcount [9:0] $end
$scope module t1 $end
$var wire 48 + dest_addr [47:0] $end
$var wire 9 , direction [8:0] $end
$var wire 1 $ eth_clk $end
$var wire 1 % eth_rst $end
$var wire 32 - fcs [31:0] $end
$var wire 3 . game_stat [2:0] $end
$var wire 11 / hcount [10:0] $end
$var wire 16 0 len [15:0] $end
$var wire 11 1 player_x [10:0] $end
$var wire 11 2 player_y [10:0] $end
$var wire 56 3 preamble [55:0] $end
$var wire 8 4 sfd [7:0] $end
$var wire 48 5 source_addr [47:0] $end
$var wire 10 6 vcount [9:0] $end
$var wire 512 7 message [511:0] $end
$var wire 40 8 data [39:0] $end
$var wire 1 9 bit_axiov $end
$var wire 2 : bit_axiod [1:0] $end
$var reg 2 ; bit_axiid [1:0] $end
$var reg 1 < bit_axiiv $end
$var reg 512 = buffer [511:0] $end
$var reg 1 > counter $end
$var reg 2 ? eth_txd [1:0] $end
$var reg 1 ! eth_txen $end
$var reg 2 @ state [1:0] $end
$scope module b1 $end
$var wire 2 A axiid [1:0] $end
$var wire 1 < axiiv $end
$var wire 1 $ clk $end
$var wire 1 % rst $end
$var reg 2 B axiod [1:0] $end
$var reg 1 9 axiov $end
$var reg 16 C b1_count [15:0] $end
$var reg 16 D b2_count [15:0] $end
$var reg 8 E buff1 [7:0] $end
$var reg 8 F buff2 [7:0] $end
$var reg 1 G read_buff1 $end
$var reg 1 H read_buff2 $end
$var reg 1 I readout_buff1 $end
$var reg 1 J readout_buff2 $end
$upscope $end
$upscope $end
$upscope $end
$enddefinitions $end
$comment Show the parameter values. $end
$dumpall
$end
#0
$dumpvars
xJ
xI
xH
xG
bx F
bx E
bx D
bx C
b0 B
bx A
bx @
bx ?
x>
bx =
x<
bx ;
b0 :
09
bx0xxxxxxxxxxx0xxxxxxxxx000xxx0 8
b1010101010101010101010101010101010101010101010101010101110101011111111111111111111111111111111111111111111111111111111111111111111111111111111111111111111111110000000000000000xxxxxxxxxxx0xxxxxxxxxxx0xxxxxxxxx000xxx000000000000000000000000000000000000000000000000000000000000000000000000000000000000000000000000000000000000000000000000000000000000000000000000000000000000000000000000000000000000000000000000000000000000000000000000000000000000000000000000000000000000000000000000011001011111101000011100100100110 7
bx 6
b111111111111111111111111111111111111111111111111 5
b11010101 4
b1010101010101010101010101010101010101010101010101010101 3
bx 2
bx 1
b0 0
bx /
bx .
b11001011111101000011100100100110 -
bx ,
b111111111111111111111111111111111111111111111111 +
bx *
bx )
bx (
bx '
bx &
1%
0$
bx #
bx "
x!
$end
#10000
0J
0I
0H
1G
b0 D
b0 C
b0 F
b0 E
b0 ;
b0 A
0<
b0 @
0>
1$
#20000
0$
b1 &
b1 .
b1011010 #
b1011010 ,
b1000 )
b1000 2
b1010101010101010101010101010101010101010101010101010101110101011111111111111111111111111111111111111111111111111111111111111111111111111111111111111111111111110000000000000000000000010000000000010000001011010000001000000000000000000000000000000000000000000000000000000000000000000000000000000000000000000000000000000000000000000000000000000000000000000000000000000000000000000000000000000000000000000000000000000000000000000000000000000000000000000000000000000000000000000000000011001011111101000011100100100110 7
b100000000000100000010110100000010 8
b1000 (
b1000 1
b0 *
b0 6
b0 '
b0 /
0%
#30000
b0 "
b0 ?
0!
1$
#40000
0$
b1100000000 *
b1100000000 6
b10000000000 '
b10000000000 /
#50000
b1 @
b1010101010101010101010101010101010101010101010101010101110101011111111111111111111111111111111111111111111111111111111111111111111111111111111111111111111111110000000000000000000000010000000000010000001011010000001000000000000000000000000000000000000000000000000000000000000000000000000000000000000000000000000000000000000000000000000000000000000000000000000000000000000000000000000000000000000000000000000000000000000000000000000000000000000000000000000000000000000000000000000011001011111101000011100100100110 =
1$
#60000
0$
b0 *
b0 6
b0 '
b0 /
#70000
b1010101010101010101010101010101010101010101010101010111010101111111111111111111111111111111111111111111111111111111111111111111111111111111111111111111111111000000000000000000000001000000000001000000101101000000100000000000000000000000000000000000000000000000000000000000000000000000000000000000000000000000000000000000000000000000000000000000000000000000000000000000000000000000000000000000000000000000000000000000000000000000000000000000000000000000000000000000000000000000001100101111110100001110010010011000 =
b1 ;
b1 A
1<
1$
#80000
0$
#90000
b1 E
b1 C
b1010101010101010101010101010101010101010101010101011101010111111111111111111111111111111111111111111111111111111111111111111111111111111111111111111111111100000000000000000000000100000000000100000010110100000010000000000000000000000000000000000000000000000000000000000000000000000000000000000000000000000000000000000000000000000000000000000000000000000000000000000000000000000000000000000000000000000000000000000000000000000000000000000000000000000000000000000000000000000000110010111111010000111001001001100000 =
1$
#100000
0$
#110000
b1010101010101010101010101010101010101010101010101110101011111111111111111111111111111111111111111111111111111111111111111111111111111111111111111111111110000000000000000000000010000000000010000001011010000001000000000000000000000000000000000000000000000000000000000000000000000000000000000000000000000000000000000000000000000000000000000000000000000000000000000000000000000000000000000000000000000000000000000000000000000000000000000000000000000000000000000000000000000000011001011111101000011100100100110000000 =
b101 E
b10 C
1$
#120000
0$
#130000
b10101 E
b11 C
b1010101010101010101010101010101010101010101010111010101111111111111111111111111111111111111111111111111111111111111111111111111111111111111111111111111000000000000000000000001000000000001000000101101000000100000000000000000000000000000000000000000000000000000000000000000000000000000000000000000000000000000000000000000000000000000000000000000000000000000000000000000000000000000000000000000000000000000000000000000000000000000000000000000000000000000000000000000000000001100101111110100001110010010011000000000 =
1$
#140000
0$
#150000
b1 :
b1 B
19
b1010101010101010101010101010101010101010101011101010111111111111111111111111111111111111111111111111111111111111111111111111111111111111111111111111100000000000000000000000100000000000100000010110100000010000000000000000000000000000000000000000000000000000000000000000000000000000000000000000000000000000000000000000000000000000000000000000000000000000000000000000000000000000000000000000000000000000000000000000000000000000000000000000000000000000000000000000000000000110010111111010000111001001001100000000000 =
1I
0G
b1010101 E
b100 C
1$
#160000
0$
#170000
b1 F
b1 D
b11 C
b1 "
b1 ?
1!
b1010101010101010101010101010101010101010101110101011111111111111111111111111111111111111111111111111111111111111111111111111111111111111111111111110000000000000000000000010000000000010000001011010000001000000000000000000000000000000000000000000000000000000000000000000000000000000000000000000000000000000000000000000000000000000000000000000000000000000000000000000000000000000000000000000000000000000000000000000000000000000000000000000000000000000000000000000000000011001011111101000011100100100110000000000000 =
1$
#180000
0$
#190000
b1010101010101010101010101010101010101010111010101111111111111111111111111111111111111111111111111111111111111111111111111111111111111111111111111000000000000000000000001000000000001000000101101000000100000000000000000000000000000000000000000000000000000000000000000000000000000000000000000000000000000000000000000000000000000000000000000000000000000000000000000000000000000000000000000000000000000000000000000000000000000000000000000000000000000000000000000000000001100101111110100001110010010011000000000000000 =
b101 F
b10 D
b10 C
1$
#200000
0$
#210000
b10101 F
b11 D
b1 C
b1010101010101010101010101010101010101011101010111111111111111111111111111111111111111111111111111111111111111111111111111111111111111111111111100000000000000000000000100000000000100000010110100000010000000000000000000000000000000000000000000000000000000000000000000000000000000000000000000000000000000000000000000000000000000000000000000000000000000000000000000000000000000000000000000000000000000000000000000000000000000000000000000000000000000000000000000000000110010111111010000111001001001100000000000000000 =
1$
#220000
0$
#230000
b1010101010101010101010101010101010101110101011111111111111111111111111111111111111111111111111111111111111111111111111111111111111111111111110000000000000000000000010000000000010000001011010000001000000000000000000000000000000000000000000000000000000000000000000000000000000000000000000000000000000000000000000000000000000000000000000000000000000000000000000000000000000000000000000000000000000000000000000000000000000000000000000000000000000000000000000000000011001011111101000011100100100110000000000000000000 =
1J
0I
b1010101 F
b100 D
b0 C
1$
#240000
0$
#250000
b1 C
b11 D
b1010101010101010101010101010101010111010101111111111111111111111111111111111111111111111111111111111111111111111111111111111111111111111111000000000000000000000001000000000001000000101101000000100000000000000000000000000000000000000000000000000000000000000000000000000000000000000000000000000000000000000000000000000000000000000000000000000000000000000000000000000000000000000000000000000000000000000000000000000000000000000000000000000000000000000000000000001100101111110100001110010010011000000000000000000000 =
1$
#260000
0$
#270000
b1010101010101010101010101010101011101010111111111111111111111111111111111111111111111111111111111111111111111111111111111111111111111111100000000000000000000000100000000000100000010110100000010000000000000000000000000000000000000000000000000000000000000000000000000000000000000000000000000000000000000000000000000000000000000000000000000000000000000000000000000000000000000000000000000000000000000000000000000000000000000000000000000000000000000000000000000110010111111010000111001001001100000000000000000000000 =
b10 C
b10 D
1$
#280000
0$
#290000
b11 C
b1 D
b1010101010101010101010101010101110101011111111111111111111111111111111111111111111111111111111111111111111111111111111111111111111111110000000000000000000000010000000000010000001011010000001000000000000000000000000000000000000000000000000000000000000000000000000000000000000000000000000000000000000000000000000000000000000000000000000000000000000000000000000000000000000000000000000000000000000000000000000000000000000000000000000000000000000000000000000011001011111101000011100100100110000000000000000000000000 =
1$
#300000
0$
#310000
b1010101010101010101010101010111010101111111111111111111111111111111111111111111111111111111111111111111111111111111111111111111111111000000000000000000000001000000000001000000101101000000100000000000000000000000000000000000000000000000000000000000000000000000000000000000000000000000000000000000000000000000000000000000000000000000000000000000000000000000000000000000000000000000000000000000000000000000000000000000000000000000000000000000000000000000001100101111110100001110010010011000000000000000000000000000 =
0J
1I
b100 C
b0 D
1$
#320000
0$
#330000
b1 D
b11 C
b1010101010101010101010101011101010111111111111111111111111111111111111111111111111111111111111111111111111111111111111111111111111100000000000000000000000100000000000100000010110100000010000000000000000000000000000000000000000000000000000000000000000000000000000000000000000000000000000000000000000000000000000000000000000000000000000000000000000000000000000000000000000000000000000000000000000000000000000000000000000000000000000000000000000000000000110010111111010000111001001001100000000000000000000000000000 =
1$
#340000
0$
#350000
b1010101010101010101010101110101011111111111111111111111111111111111111111111111111111111111111111111111111111111111111111111111110000000000000000000000010000000000010000001011010000001000000000000000000000000000000000000000000000000000000000000000000000000000000000000000000000000000000000000000000000000000000000000000000000000000000000000000000000000000000000000000000000000000000000000000000000000000000000000000000000000000000000000000000000000011001011111101000011100100100110000000000000000000000000000000 =
b10 D
b10 C
1$
#360000
0$
#370000
b11 D
b1 C
b1010101010101010101010111010101111111111111111111111111111111111111111111111111111111111111111111111111111111111111111111111111000000000000000000000001000000000001000000101101000000100000000000000000000000000000000000000000000000000000000000000000000000000000000000000000000000000000000000000000000000000000000000000000000000000000000000000000000000000000000000000000000000000000000000000000000000000000000000000000000000000000000000000000000000001100101111110100001110010010011000000000000000000000000000000000 =
1$
#380000
0$
#390000
b1010101010101010101011101010111111111111111111111111111111111111111111111111111111111111111111111111111111111111111111111111100000000000000000000000100000000000100000010110100000010000000000000000000000000000000000000000000000000000000000000000000000000000000000000000000000000000000000000000000000000000000000000000000000000000000000000000000000000000000000000000000000000000000000000000000000000000000000000000000000000000000000000000000000000110010111111010000111001001001100000000000000000000000000000000000 =
1J
0I
b100 D
b0 C
1$
#400000
0$
#410000
b1 C
b11 D
b1010101010101010101110101011111111111111111111111111111111111111111111111111111111111111111111111111111111111111111111111110000000000000000000000010000000000010000001011010000001000000000000000000000000000000000000000000000000000000000000000000000000000000000000000000000000000000000000000000000000000000000000000000000000000000000000000000000000000000000000000000000000000000000000000000000000000000000000000000000000000000000000000000000000011001011111101000011100100100110000000000000000000000000000000000000 =
1$
#420000
0$
#430000
b1010101010101010111010101111111111111111111111111111111111111111111111111111111111111111111111111111111111111111111111111000000000000000000000001000000000001000000101101000000100000000000000000000000000000000000000000000000000000000000000000000000000000000000000000000000000000000000000000000000000000000000000000000000000000000000000000000000000000000000000000000000000000000000000000000000000000000000000000000000000000000000000000000000001100101111110100001110010010011000000000000000000000000000000000000000 =
b10 C
b10 D
1$
#440000
0$
#450000
b11 C
b1 D
b1010101010101011101010111111111111111111111111111111111111111111111111111111111111111111111111111111111111111111111111100000000000000000000000100000000000100000010110100000010000000000000000000000000000000000000000000000000000000000000000000000000000000000000000000000000000000000000000000000000000000000000000000000000000000000000000000000000000000000000000000000000000000000000000000000000000000000000000000000000000000000000000000000000110010111111010000111001001001100000000000000000000000000000000000000000 =
1$
#460000
0$
#470000
b1010101010101110101011111111111111111111111111111111111111111111111111111111111111111111111111111111111111111111111110000000000000000000000010000000000010000001011010000001000000000000000000000000000000000000000000000000000000000000000000000000000000000000000000000000000000000000000000000000000000000000000000000000000000000000000000000000000000000000000000000000000000000000000000000000000000000000000000000000000000000000000000000000011001011111101000011100100100110000000000000000000000000000000000000000000 =
0J
1I
b100 C
b0 D
1$
#480000
0$
#490000
b1 D
b11 C
b1010101010111010101111111111111111111111111111111111111111111111111111111111111111111111111111111111111111111111111000000000000000000000001000000000001000000101101000000100000000000000000000000000000000000000000000000000000000000000000000000000000000000000000000000000000000000000000000000000000000000000000000000000000000000000000000000000000000000000000000000000000000000000000000000000000000000000000000000000000000000000000000000001100101111110100001110010010011000000000000000000000000000000000000000000000 =
1$
#500000
0$
#510000
b1010101011101010111111111111111111111111111111111111111111111111111111111111111111111111111111111111111111111111100000000000000000000000100000000000100000010110100000010000000000000000000000000000000000000000000000000000000000000000000000000000000000000000000000000000000000000000000000000000000000000000000000000000000000000000000000000000000000000000000000000000000000000000000000000000000000000000000000000000000000000000000000000110010111111010000111001001001100000000000000000000000000000000000000000000000 =
b10 D
b10 C
1$
#520000
0$
#530000
b11 D
b1 C
b1010101110101011111111111111111111111111111111111111111111111111111111111111111111111111111111111111111111111110000000000000000000000010000000000010000001011010000001000000000000000000000000000000000000000000000000000000000000000000000000000000000000000000000000000000000000000000000000000000000000000000000000000000000000000000000000000000000000000000000000000000000000000000000000000000000000000000000000000000000000000000000000011001011111101000011100100100110000000000000000000000000000000000000000000000000 =
1$
#540000
0$
#550000
b1010111010101111111111111111111111111111111111111111111111111111111111111111111111111111111111111111111111111000000000000000000000001000000000001000000101101000000100000000000000000000000000000000000000000000000000000000000000000000000000000000000000000000000000000000000000000000000000000000000000000000000000000000000000000000000000000000000000000000000000000000000000000000000000000000000000000000000000000000000000000000000001100101111110100001110010010011000000000000000000000000000000000000000000000000000 =
1J
0I
b100 D
b0 C
1$
#560000
0$
#570000
b1 C
b11 D
b1011101010111111111111111111111111111111111111111111111111111111111111111111111111111111111111111111111111100000000000000000000000100000000000100000010110100000010000000000000000000000000000000000000000000000000000000000000000000000000000000000000000000000000000000000000000000000000000000000000000000000000000000000000000000000000000000000000000000000000000000000000000000000000000000000000000000000000000000000000000000000000110010111111010000111001001001100000000000000000000000000000000000000000000000000000 =
1$
#580000
0$
#590000
b1110101011111111111111111111111111111111111111111111111111111111111111111111111111111111111111111111111110000000000000000000000010000000000010000001011010000001000000000000000000000000000000000000000000000000000000000000000000000000000000000000000000000000000000000000000000000000000000000000000000000000000000000000000000000000000000000000000000000000000000000000000000000000000000000000000000000000000000000000000000000000011001011111101000011100100100110000000000000000000000000000000000000000000000000000000 =
b10 C
b10 D
1$
#600000
0$
#610000
b11 C
b1 D
b11010101111111111111111111111111111111111111111111111111111111111111111111111111111111111111111111111111000000000000000000000001000000000001000000101101000000100000000000000000000000000000000000000000000000000000000000000000000000000000000000000000000000000000000000000000000000000000000000000000000000000000000000000000000000000000000000000000000000000000000000000000000000000000000000000000000000000000000000000000000000001100101111110100001110010010011000000000000000000000000000000000000000000000000000000000 =
1$
#620000
0$
#630000
b1010111111111111111111111111111111111111111111111111111111111111111111111111111111111111111111111111100000000000000000000000100000000000100000010110100000010000000000000000000000000000000000000000000000000000000000000000000000000000000000000000000000000000000000000000000000000000000000000000000000000000000000000000000000000000000000000000000000000000000000000000000000000000000000000000000000000000000000000000000000000110010111111010000111001001001100000000000000000000000000000000000000000000000000000000000 =
b11 ;
b11 A
0J
1I
b100 C
b0 D
1$
#640000
0$
#650000
b1010111 F
b1 D
b11 C
b1011111111111111111111111111111111111111111111111111111111111111111111111111111111111111111111111110000000000000000000000010000000000010000001011010000001000000000000000000000000000000000000000000000000000000000000000000000000000000000000000000000000000000000000000000000000000000000000000000000000000000000000000000000000000000000000000000000000000000000000000000000000000000000000000000000000000000000000000000000000011001011111101000011100100100110000000000000000000000000000000000000000000000000000000000000 =
b1 ;
b1 A
1$
#660000
0$
#670000
b1111111111111111111111111111111111111111111111111111111111111111111111111111111111111111111111111000000000000000000000001000000000001000000101101000000100000000000000000000000000000000000000000000000000000000000000000000000000000000000000000000000000000000000000000000000000000000000000000000000000000000000000000000000000000000000000000000000000000000000000000000000000000000000000000000000000000000000000000000000001100101111110100001110010010011000000000000000000000000000000000000000000000000000000000000000 =
b10 D
b10 C
1$
#680000
0$
#690000
b11 D
b1 C
b11111111111111111111111111111111111111111111111111111111111111111111111111111111111111111111111100000000000000000000000100000000000100000010110100000010000000000000000000000000000000000000000000000000000000000000000000000000000000000000000000000000000000000000000000000000000000000000000000000000000000000000000000000000000000000000000000000000000000000000000000000000000000000000000000000000000000000000000000000000110010111111010000111001001001100000000000000000000000000000000000000000000000000000000000000000 =
1$
#700000
0$
#710000
b11111111111111111111111111111111111111111111111111111111111111111111111111111111111111111111110000000000000000000000010000000000010000001011010000001000000000000000000000000000000000000000000000000000000000000000000000000000000000000000000000000000000000000000000000000000000000000000000000000000000000000000000000000000000000000000000000000000000000000000000000000000000000000000000000000000000000000000000000000011001011111101000011100100100110000000000000000000000000000000000000000000000000000000000000000000 =
b11 ;
b11 A
1J
0I
b100 D
b0 C
1$
#720000
0$
#730000
b1010111 E
b1 C
b11 D
b11111111111111111111111111111111111111111111111111111111111111111111111111111111111111111111000000000000000000000001000000000001000000101101000000100000000000000000000000000000000000000000000000000000000000000000000000000000000000000000000000000000000000000000000000000000000000000000000000000000000000000000000000000000000000000000000000000000000000000000000000000000000000000000000000000000000000000000000000001100101111110100001110010010011000000000000000000000000000000000000000000000000000000000000000000000 =
1$
#740000
0$
#750000
b11111111111111111111111111111111111111111111111111111111111111111111111111111111111111111100000000000000000000000100000000000100000010110100000010000000000000000000000000000000000000000000000000000000000000000000000000000000000000000000000000000000000000000000000000000000000000000000000000000000000000000000000000000000000000000000000000000000000000000000000000000000000000000000000000000000000000000000000000110010111111010000111001001001100000000000000000000000000000000000000000000000000000000000000000000000 =
b1011111 E
b10 C
b10 D
1$
#760000
0$
#770000
b11 :
b11 B
b1111111 E
b11 C
b1 D
b11111111111111111111111111111111111111111111111111111111111111111111111111111111111111110000000000000000000000010000000000010000001011010000001000000000000000000000000000000000000000000000000000000000000000000000000000000000000000000000000000000000000000000000000000000000000000000000000000000000000000000000000000000000000000000000000000000000000000000000000000000000000000000000000000000000000000000000000011001011111101000011100100100110000000000000000000000000000000000000000000000000000000000000000000000000 =
1$
#780000
0$
#790000
b11 "
b11 ?
b11111111111111111111111111111111111111111111111111111111111111111111111111111111111111000000000000000000000001000000000001000000101101000000100000000000000000000000000000000000000000000000000000000000000000000000000000000000000000000000000000000000000000000000000000000000000000000000000000000000000000000000000000000000000000000000000000000000000000000000000000000000000000000000000000000000000000000000001100101111110100001110010010011000000000000000000000000000000000000000000000000000000000000000000000000000 =
0J
1I
b11111111 E
b100 C
b0 D
1$
#800000
0$
#810000
b1 D
b11 C
b11111111111111111111111111111111111111111111111111111111111111111111111111111111111100000000000000000000000100000000000100000010110100000010000000000000000000000000000000000000000000000000000000000000000000000000000000000000000000000000000000000000000000000000000000000000000000000000000000000000000000000000000000000000000000000000000000000000000000000000000000000000000000000000000000000000000000000000110010111111010000111001001001100000000000000000000000000000000000000000000000000000000000000000000000000000 =
1$
#820000
0$
#830000
b11111111111111111111111111111111111111111111111111111111111111111111111111111111110000000000000000000000010000000000010000001011010000001000000000000000000000000000000000000000000000000000000000000000000000000000000000000000000000000000000000000000000000000000000000000000000000000000000000000000000000000000000000000000000000000000000000000000000000000000000000000000000000000000000000000000000000000011001011111101000011100100100110000000000000000000000000000000000000000000000000000000000000000000000000000000 =
b1011111 F
b10 D
b10 C
1$
#840000
0$
#850000
b1111111 F
b11 D
b1 C
b11111111111111111111111111111111111111111111111111111111111111111111111111111111000000000000000000000001000000000001000000101101000000100000000000000000000000000000000000000000000000000000000000000000000000000000000000000000000000000000000000000000000000000000000000000000000000000000000000000000000000000000000000000000000000000000000000000000000000000000000000000000000000000000000000000000000000001100101111110100001110010010011000000000000000000000000000000000000000000000000000000000000000000000000000000000 =
1$
#860000
0$
#870000
b11111111111111111111111111111111111111111111111111111111111111111111111111111100000000000000000000000100000000000100000010110100000010000000000000000000000000000000000000000000000000000000000000000000000000000000000000000000000000000000000000000000000000000000000000000000000000000000000000000000000000000000000000000000000000000000000000000000000000000000000000000000000000000000000000000000000000110010111111010000111001001001100000000000000000000000000000000000000000000000000000000000000000000000000000000000 =
1J
0I
b11111111 F
b100 D
b0 C
1$
#880000
0$
#890000
b1 C
b11 D
b11111111111111111111111111111111111111111111111111111111111111111111111111110000000000000000000000010000000000010000001011010000001000000000000000000000000000000000000000000000000000000000000000000000000000000000000000000000000000000000000000000000000000000000000000000000000000000000000000000000000000000000000000000000000000000000000000000000000000000000000000000000000000000000000000000000000011001011111101000011100100100110000000000000000000000000000000000000000000000000000000000000000000000000000000000000 =
1$
#900000
0$
#910000
b11111111111111111111111111111111111111111111111111111111111111111111111111000000000000000000000001000000000001000000101101000000100000000000000000000000000000000000000000000000000000000000000000000000000000000000000000000000000000000000000000000000000000000000000000000000000000000000000000000000000000000000000000000000000000000000000000000000000000000000000000000000000000000000000000000000001100101111110100001110010010011000000000000000000000000000000000000000000000000000000000000000000000000000000000000000 =
b10 C
b10 D
1$
